GATE MODELING/5/2-1 MUX/21MUX.v
module mux21(input D0, D1, S, output Y);

wire T1;
//T1 = D1(S)
wire T2;
//T2 = D0(S)
wire X;
//X = S' 

and (T1, D1, S);
and (T2, D0, X);
not (X, S);
or (Y, T1, T2);

endmodule

GATE MODELING/5/2-1 MUX/21MUX_tb.v
`timescale 1ns/1ns
`include "21MUX.v"

module mux21_tb;

wire out;
reg d0, d1, s;

mux21 wew(.Y(out), .D0(d0), .D1(d1), .S(s));

initial begin
    $dumpfile("mux21_tb.vcd");
    $dumpvars(0, mux21_tb);

    d0=1'b0;
    d1=1'b0;
    s=1'b0;
    #100 $finish;
end

always #40 d0=~d0;
always #20 d1=~d1;
always #10 s=~s;
always@(d0 or d1 or s)

$monitor("At time = %t, Y = %d", $time, out);

endmodule;

GATE MODELING/5/2-1 MUX/mux21_tb.vcd
$date
	Mon Sep 20 19:08:03 2021
$end
$version
	Icarus Verilog
$end
$timescale
	1ns
$end
$scope module mux21_tb $end
$var wire 1 ! out $end
$var reg 1 " d0 $end
$var reg 1 # d1 $end
$var reg 1 $ s $end
$scope module wew $end
$var wire 1 " D0 $end
$var wire 1 # D1 $end
$var wire 1 $ S $end
$var wire 1 % T1 $end
$var wire 1 & T2 $end
$var wire 1 ' X $end
$var wire 1 ! Y $end
$upscope $end
$upscope $end
$enddefinitions $end
#0
$dumpvars
1'
0&
0%
0$
0#
0"
0!
$end
#10
0'
1$
#20
1'
0$
1#
#30
1!
1%
0'
1$
#40
1&
1!
1'
0%
0$
0#
1"
#50
0!
0&
0'
1$
#60
1!
1&
1'
0$
1#
#70
0&
1%
0'
1$
#80
0!
1'
0%
0$
0#
0"
#90
0'
1$
#100
1'
0$
1#
