Activity 3/3/bytecomp.v
module bytecomparator( a, b, en, f); 

input [7:0] a, b;
input en;
output f;
 
wire [7:0] c;
wire d;

  xor g1 [7:0] (c,a,b);
  or (d,c);
  notif1 notif_1(f,d,en);

endmodule

Activity 3/3/bytecomp_tb.v
`timescale 1ns / 1ns
`include "bytecomp.v"

module bytecomparator_tb;

reg[7:0]a,b;
reg en;

bytecomparator wew(.f(f),.a(a),.b(b),.en(en));

initial begin
    $dumpfile("bytecomparator_tb.vcd");
    $dumpvars(0, bytecomparator_tb);

a = 8'b00000000;

b = 8'b00000000;

en = 1'b0;

end

always

#2 en = 1'b1;

always

begin

 #2 a = a+1'b1;

 #2 b = b+1'b0;

end

initial $monitor($time," en = %b , a = %b ,b = %b ,f = %b ",en,a,b,f);

initial 
#30 
$stop;

endmodule

Activity 3/3/bytecomparator_tb.vcd
$date
	Sun Sep 26 16:25:46 2021
$end
$version
	Icarus Verilog
$end
$timescale
	1ns
$end
$scope module bytecomparator_tb $end
$var wire 1 ! f $end
$var reg 8 " a [7:0] $end
$var reg 8 # b [7:0] $end
$var reg 1 $ en $end
$scope module wew $end
$var wire 8 % a [7:0] $end
$var wire 8 & b [7:0] $end
$var wire 8 ' c [7:0] $end
$var wire 1 ( d $end
$var wire 1 $ en $end
$var wire 1 ! f $end
$upscope $end
$upscope $end
$enddefinitions $end
#0
$dumpvars
0(
b0 '
b0 &
b0 %
0$
b0 #
b0 "
z!
$end
#2
1(
b1 '
b1 "
b1 %
0!
1$
#6
1!
0(
b10 '
b10 "
b10 %
#10
0!
1(
b11 '
b11 "
b11 %
#14
1!
0(
b100 '
b100 "
b100 %
#18
0!
1(
b101 '
b101 "
b101 %
#22
1!
0(
b110 '
b110 "
b110 %
#26
0!
1(
b111 '
b111 "
b111 %
